pysolarfocus/__init__.py
pysolarfocus/component_factory.py
pysolarfocus/const.py
pysolarfocus/modbus_wrapper.py
pysolarfocus/components/__init__.py
pysolarfocus/components/biomass_boiler.py
pysolarfocus/components/boiler.py
pysolarfocus/components/buffer.py
pysolarfocus/components/circulation.py
pysolarfocus/components/differential_module.py
pysolarfocus/components/fresh_water_module.py
pysolarfocus/components/heat_pump.py
pysolarfocus/components/heating_circuit.py
pysolarfocus/components/photovoltaic.py
pysolarfocus/components/solar.py
pysolarfocus/components/base/__init__.py
pysolarfocus/components/base/component.py
pysolarfocus/components/base/data_value.py
pysolarfocus/components/base/enums.py
pysolarfocus/components/base/part.py
pysolarfocus/components/base/performance_calculator.py
pysolarfocus/components/base/register_slice.py
pysolarfocus-5.1.2.dist-info/METADATA
pysolarfocus-5.1.2.dist-info/WHEEL
pysolarfocus-5.1.2.dist-info/licenses/LICENSE
pysolarfocus-5.1.2.dist-info/RECORD
