Metadata-Version: 2.4
Name: pysolarfocus
Version: 5.1.2
Summary: Unofficial, local Solarfocus client
Project-URL: Homepage, https://github.com/lavermanjj/pysolarfocus
Project-URL: Repository, https://github.com/lavermanjj/pysolarfocus
Author-email: Jeroen Laverman <jjlaverman@web.de>
License-Expression: Apache-2.0
License-File: LICENSE
Keywords: api client,solarfocus
Requires-Python: ~=3.11
Requires-Dist: packaging~=24.0
Requires-Dist: pymodbus<4,>=3.2.2
